vish_print/__init__.py
vish_print/formatter.py
vish_print/printer.py
vish_print-0.1.0.dist-info/METADATA
vish_print-0.1.0.dist-info/WHEEL
vish_print-0.1.0.dist-info/top_level.txt
vish_print-0.1.0.dist-info/RECORD
