Metadata-Version: 2.1
Name: vish_print
Version: 0.1.0
Summary: An advanced print function with formatting and logging
Author: Vishango
Author-email: itsvishalhack@gmail.com
